{
  "settings": {
    "flashcardEasyText": "Easy",
    "flashcardGoodText": "Good",
    "flashcardHardText": "Hard/Incorrect",
    "flashcardTags": [
      "#test",
      "#cisco",
      "#fil",
      "#os",
      "#ai"
    ],
    "convertFoldersToDecks": false,
    "cardCommentOnSameLine": true,
    "burySiblingCards": false,
    "showContextInCards": true,
    "flashcardHeightPercentage": 80,
    "flashcardWidthPercentage": 40,
    "randomizeCardOrder": null,
    "flashcardCardOrder": "DueFirstRandom",
    "flashcardDeckOrder": "PrevDeckComplete_Sequential",
    "convertHighlightsToClozes": true,
    "convertBoldTextToClozes": false,
    "convertCurlyBracketsToClozes": true,
    "singleLineCardSeparator": ";;",
    "singleLineReversedCardSeparator": ";;;",
    "multilineCardSeparator": ",,",
    "multilineReversedCardSeparator": ",,,",
    "editLaterTag": "#edit-later",
    "enableNoteReviewPaneOnStartup": true,
    "tagsToReview": [
      "#review"
    ],
    "noteFoldersToIgnore": [],
    "openRandomNote": false,
    "autoNextNote": false,
    "disableFileMenuReviewOptions": false,
    "maxNDaysNotesReviewQueue": 365,
    "initiallyExpandAllSubdecksInTree": false,
    "baseEase": 130,
    "lapsesIntervalChange": 0.01,
    "easyBonus": 1.3,
    "maximumInterval": 36525,
    "maxLinkFactor": 1,
    "showDebugMessages": false,
    "showFileNameInFileLink": true,
    "singlelineCardSeparator": ";;",
    "singlelineReversedCardSeparator": ";;;"
  },
  "buryDate": "2024-10-16",
  "buryList": [],
  "historyDeck": ""
}